{
  "schema": "Axiom-ZSpace Existing Planet Card v1.0",
  "zspace_id": "ZS-T-149918151-01",
  "timestamp_utc": "2026-04-26T11:32:21.449890+00:00",
  "status": "KNOWN",
  "match_source": "TOI",
  "match_summary": {
    "planet_name": "3846.01",
    "period_delta_days": 0.00053857,
    "tolerance_days": 0.01,
    "proof": "|P_candidate - P_archive| = 0.00053857 d \u2264 0.01 d \u2192 MATCH"
  },
  "candidate_parameters": {
    "tic_id": "149918151",
    "period_days": 1.5402374293704695,
    "transit_depth_ppm": 24998.75,
    "planet_radius_earth": 13.268409854762439,
    "stellar_mass_solar": 0.662,
    "stellar_radius_solar": 0.769359,
    "stellar_teff_k": 4234.0,
    "cvs_score": 1.0,
    "cvs_verdict": "PLANET CANDIDATE"
  },
  "archive_parameters": {
    "planet_name": "3846.01",
    "period_days_archive": 1.540776,
    "transit_depth_archive": 27310.0,
    "planet_radius_earth": 13.3674,
    "semi_major_axis_au": null,
    "stellar_teff_k": 4234.0,
    "stellar_radius_solar": 0.77,
    "stellar_mass_solar": null,
    "discovery_method": "Transit (TESS)",
    "disposition": "KP",
    "extra_fields": {
      "tmag": 12.9178,
      "period_alias_factor": 1.0
    }
  },
  "parameter_deltas": {
    "period_delta_days": 0.00053857,
    "period_delta_pct": -0.035,
    "depth_delta_ppm": -27309975001.25,
    "radius_delta_pct": -0.7405
  },
  "all_archive_entries_for_tic": [],
  "all_toi_entries_for_tic": [
    {
      "toi": "3846.01",
      "tid": 149918151,
      "pl_orbper": 1.540776,
      "pl_trandep": 27310.0,
      "pl_trandurh": 1.705,
      "tfopwg_disp": "KP",
      "ra": 160.748095,
      "dec": 60.964119,
      "st_tmag": 12.9178,
      "st_teff": 4234.0,
      "st_logg": 4.49,
      "st_rad": 0.77,
      "pl_rade": 13.3674
    }
  ]
}